mcp_pkm_logseq/__init__.py
mcp_pkm_logseq/request.py
mcp_pkm_logseq/request_test.py
mcp_pkm_logseq/server.py
mcp_pkm_logseq/server_test.py
mcp_pkm_logseq/to_markdown.py
mcp_pkm_logseq/to_markdown_test.py
mcp_pkm_logseq-0.2.2.dist-info/METADATA
mcp_pkm_logseq-0.2.2.dist-info/WHEEL
mcp_pkm_logseq-0.2.2.dist-info/entry_points.txt
mcp_pkm_logseq-0.2.2.dist-info/licenses/LICENSE
mcp_pkm_logseq-0.2.2.dist-info/RECORD
