Metadata-Version: 2.4
Name: mcp-pkm-logseq
Version: 0.2.2
Summary: A MCP server for interacting with your Logseq Personal Knowledge Management system using custom instructions
Author-email: Ronie Uliana <ronie.uliana@gmail.com>
License-File: LICENSE
Requires-Python: >=3.12
Requires-Dist: mcp[cli]>=1.6.0
Requires-Dist: requests>=2.32.3
Provides-Extra: test
Requires-Dist: pytest<9.0.0,>=8.0.0; extra == 'test'
Requires-Dist: requests-mock<2.0.0,>=1.12.0; extra == 'test'
